{
  "type": "Feature",
  "properties": {
    "gn:admin1_code":"030",
    "gn:asciiname":"Ailuk",
    "gn:cc2":"MH",
    "gn:country_code":"MH",
    "gn:dem":10,
    "gn:feature_class":"P",
    "gn:feature_code":"PPLA",
    "gn:name":"Ailuk",
    "gn:population":451,
    "gn:timezone":"Pacific/Majuro",
    "iso:country":"MH",
    "name:und_x_variant":[
        "Enellik Island"
    ],
    "wof:name":"Ailuk",
    "wof:placetype":"locality",
    "wof:population":451
},
  "geometry": {"coordinates":[169.97967,10.21972],"type":"Point"}
}