{
  "type": "Feature",
  "properties": {
    "iso:country":"MH",
    "name:ceb_x_preferred":[
        "Lib Island"
    ],
    "name:deu_x_preferred":[
        "Lib"
    ],
    "name:eng_x_preferred":[
        "Lib"
    ],
    "name:eng_x_variant":[
        "Lib Island"
    ],
    "name:fas_x_preferred":[
        "\u062c\u0632\u06cc\u0631\u0647 \u0644\u06cc\u0628"
    ],
    "name:fin_x_preferred":[
        "Lib"
    ],
    "name:fra_x_preferred":[
        "Lib"
    ],
    "name:glg_x_preferred":[
        "Lib"
    ],
    "name:hrv_x_preferred":[
        "Lib"
    ],
    "name:ind_x_preferred":[
        "Pulau Lib"
    ],
    "name:ita_x_preferred":[
        "Lib"
    ],
    "name:jpn_x_preferred":[
        "\u30ea\u30d6\u5cf6"
    ],
    "name:kor_x_preferred":[
        "\ub9ac\ube0c\uc12c"
    ],
    "name:lit_x_preferred":[
        "Libas"
    ],
    "name:mkd_x_preferred":[
        "\u041b\u0438\u0431"
    ],
    "name:nld_x_preferred":[
        "Lib Island"
    ],
    "name:pol_x_preferred":[
        "Lib"
    ],
    "name:rus_x_preferred":[
        "\u041b\u0438\u0431"
    ],
    "name:spa_x_preferred":[
        "Lib"
    ],
    "name:swe_x_preferred":[
        "Lib"
    ],
    "name:zho_x_preferred":[
        "\u91cc\u5e03\u5cf6"
    ],
    "qs:gn_country":"MH",
    "qs:gn_fcode":"ADM1",
    "qs:gn_pop":147,
    "qs:name":"Lib",
    "qs:name_adm0":"Marshall Islands",
    "qs:name_adm1":"Lib",
    "qs:photos":0,
    "qs:photos_1k":0,
    "qs:photos_9k":0,
    "qs:photos_9r":0,
    "qs:photos_all":0,
    "qs:photos_sr":0,
    "qs:placetype":"State",
    "qs:pop_sr":"1",
    "qs:woe_adm0":23424932,
    "wof:lang_x_official":[
        "eng",
        "mah"
    ],
    "wof:lang_x_spoken":[
        "eng",
        "mah"
    ],
    "wof:name":"Lib",
    "wof:placetype":"region",
    "wof:population":147
},
  "geometry": {"coordinates":[167.38,8.3136],"type":"Point"}
}