{
  "type": "Feature",
  "properties": {
    "gn:admin1_code":"320",
    "gn:asciiname":"Kinnatkan",
    "gn:country_code":"MH",
    "gn:dem":8,
    "gn:feature_class":"P",
    "gn:feature_code":"PPL",
    "gn:name":"Kinnatkan",
    "gn:population":0,
    "gn:timezone":"Pacific/Majuro",
    "iso:country":"MH",
    "wof:name":"Kinnatkan",
    "wof:placetype":"locality"
},
  "geometry": {"coordinates":[171.89694,6.07006],"type":"Point"}
}