{
  "type": "Feature",
  "properties": {
    "gn:admin1_code":"010",
    "gn:asciiname":"Airok",
    "gn:country_code":"MH",
    "gn:dem":16,
    "gn:feature_class":"P",
    "gn:feature_code":"PPL",
    "gn:name":"Airok",
    "gn:population":0,
    "gn:timezone":"Pacific/Majuro",
    "iso:country":"MH",
    "name:eng_x_preferred":[
        "Airok"
    ],
    "name:und_x_variant":[
        "Airuk",
        "Airekku-to *"
    ],
    "wof:name":"Airok",
    "wof:placetype":"locality"
},
  "geometry": {"coordinates":[168.82166999999995,7.27861],"type":"Point"}
}