{
  "type": "Feature",
  "properties": {
    "gn:admin1_code":"150",
    "gn:asciiname":"Enubuj",
    "gn:country_code":"MH",
    "gn:dem":14,
    "gn:feature_class":"P",
    "gn:feature_code":"PPL",
    "gn:name":"Enubuj",
    "gn:population":0,
    "gn:timezone":"Pacific/Kwajalein",
    "iso:country":"MH",
    "wof:name":"Enubuj",
    "wof:placetype":"locality"
},
  "geometry": {"coordinates":[167.68504999999999,8.7484],"type":"Point"}
}