{
  "type": "Feature",
  "properties": {
    "gn:admin1_code":"040",
    "gn:asciiname":"Ine",
    "gn:country_code":"MH",
    "gn:dem":10,
    "gn:feature_class":"P",
    "gn:feature_code":"PPL",
    "gn:name":"Ine",
    "gn:population":0,
    "gn:timezone":"Pacific/Majuro",
    "iso:country":"MH",
    "wof:name":"Ine",
    "wof:placetype":"locality"
},
  "geometry": {"coordinates":[171.69999999999999,6.98333],"type":"Point"}
}