{
  "type": "Feature",
  "properties": {
    "gn:country":"MH",
    "gn:fcode":"ATOL",
    "gn:population":322,
    "iso:country":"MH",
    "name:ceb_x_preferred":[
        "Lae"
    ],
    "name:deu_x_preferred":[
        "Lae-Atoll"
    ],
    "name:eng_x_preferred":[
        "Lae Atoll"
    ],
    "name:fas_x_preferred":[
        "\u0622\u0628\u200c\u0633\u0646\u06af \u062d\u0644\u0642\u0648\u06cc \u0644\u0627\u0626\u0647"
    ],
    "name:fin_x_preferred":[
        "Lae"
    ],
    "name:fra_x_preferred":[
        "Lae"
    ],
    "name:glg_x_preferred":[
        "Atol Lae"
    ],
    "name:hrv_x_preferred":[
        "Lae"
    ],
    "name:ind_x_preferred":[
        "Atol Lae"
    ],
    "name:ita_x_preferred":[
        "Lae"
    ],
    "name:jpn_x_preferred":[
        "\u30e9\u30a8\u30fc\u74b0\u7901"
    ],
    "name:kor_x_preferred":[
        "\ub77c\uc5d0 \ud658\ucd08"
    ],
    "name:lit_x_preferred":[
        "La\u0117"
    ],
    "name:mkd_x_preferred":[
        "\u041b\u0430\u0435"
    ],
    "name:nld_x_preferred":[
        "Lae Atoll"
    ],
    "name:pol_x_preferred":[
        "Lea"
    ],
    "name:por_x_preferred":[
        "Atol Lae"
    ],
    "name:rus_x_preferred":[
        "\u041b\u0430\u044d"
    ],
    "name:spa_x_preferred":[
        "Lae"
    ],
    "name:swe_x_preferred":[
        "Lae"
    ],
    "name:und_x_variant":[
        "Brown Island"
    ],
    "name:zho_x_preferred":[
        "\u62c9\u57c3\u74b0\u7901"
    ],
    "qs:name":"Lae Atoll",
    "qs:photos_9r":0,
    "qs:photos_sr":0,
    "qs:pop_sr":"2",
    "wd:wordcount":185,
    "wof:name":"Lae Atoll",
    "wof:placetype":"locality",
    "wof:population":322
},
  "geometry": {"coordinates":[166.23181,8.93408],"type":"Point"}
}