{
  "type": "Feature",
  "properties": {
    "gn:country":"MH",
    "gn:fcode":"ATOL",
    "gn:pop":322,
    "iso:country":"MH",
    "name:chi_x_preferred":[
        "\u62c9\u57c3\u74b0\u7901"
    ],
    "name:dut_x_preferred":[
        "Lae Atoll"
    ],
    "name:eng_x_preferred":[
        "Lae Atoll"
    ],
    "name:fin_x_preferred":[
        "Lae"
    ],
    "name:fre_x_preferred":[
        "Lae"
    ],
    "name:ger_x_preferred":[
        "Lae-Atoll"
    ],
    "name:glg_x_preferred":[
        "Atol Lae"
    ],
    "name:hrv_x_preferred":[
        "Lae"
    ],
    "name:ita_x_preferred":[
        "Lae"
    ],
    "name:jpn_x_preferred":[
        "\u30e9\u30a8\u30fc\u74b0\u7901"
    ],
    "name:kor_x_preferred":[
        "\ub77c\uc5d0 \ud658\ucd08"
    ],
    "name:lit_x_preferred":[
        "La\u0117"
    ],
    "name:mac_x_preferred":[
        "\u041b\u0430\u0435"
    ],
    "name:pol_x_preferred":[
        "Lea"
    ],
    "name:por_x_preferred":[
        "Atol Lae"
    ],
    "name:rus_x_preferred":[
        "\u041b\u0430\u044d"
    ],
    "name:spa_x_preferred":[
        "Lae"
    ],
    "name:swe_x_preferred":[
        "Lae"
    ],
    "name:unk_x_variant":[
        "Brown Island"
    ],
    "qs:name":"Lae Atoll",
    "qs:photos_9r":0,
    "qs:photos_sr":0,
    "qs:pop_sr":"2",
    "wd:wordcount":185,
    "wof:name":"Lae Atoll",
    "wof:placetype":"locality",
    "wof:population":322
},
  "geometry": {"coordinates":[166.23181,8.93408],"type":"Point"}
}