{
  "type": "Feature",
  "properties": {
    "gn:country":"MH",
    "gn:fcode":"ISL",
    "gn:pop":147,
    "iso:country":"MH",
    "name:unk_x_variant":[
        "Elleb"
    ],
    "qs:name":"Lib Island",
    "qs:photos_9r":0,
    "qs:photos_sr":0,
    "qs:pop_sr":"1",
    "wd:wordcount":163,
    "wof:name":"Lib Island",
    "wof:placetype":"locality",
    "wof:population":147
},
  "geometry": {"coordinates":[167.37860000000001,8.31444],"type":"Point"}
}