{
  "type": "Feature",
  "properties": {
    "gn:country":"MH",
    "gn:fcode":"ISL",
    "gn:population":147,
    "iso:country":"MH",
    "name:ceb_x_preferred":[
        "Lib Island"
    ],
    "name:deu_x_preferred":[
        "Lib"
    ],
    "name:eng_x_preferred":[
        "Lib Island"
    ],
    "name:fas_x_preferred":[
        "\u062c\u0632\u06cc\u0631\u0647 \u0644\u06cc\u0628"
    ],
    "name:fin_x_preferred":[
        "Lib"
    ],
    "name:fra_x_preferred":[
        "Lib"
    ],
    "name:glg_x_preferred":[
        "Lib"
    ],
    "name:hrv_x_preferred":[
        "Lib"
    ],
    "name:ind_x_preferred":[
        "Pulau Lib"
    ],
    "name:ita_x_preferred":[
        "Lib"
    ],
    "name:jpn_x_preferred":[
        "\u30ea\u30d6\u5cf6"
    ],
    "name:kor_x_preferred":[
        "\ub9ac\ube0c\uc12c"
    ],
    "name:lit_x_preferred":[
        "Libas"
    ],
    "name:mkd_x_preferred":[
        "\u041b\u0438\u0431"
    ],
    "name:nld_x_preferred":[
        "Lib Island"
    ],
    "name:pol_x_preferred":[
        "Lib"
    ],
    "name:rus_x_preferred":[
        "\u041b\u0438\u0431"
    ],
    "name:spa_x_preferred":[
        "Lib"
    ],
    "name:swe_x_preferred":[
        "Lib"
    ],
    "name:und_x_variant":[
        "Elleb"
    ],
    "name:urd_x_preferred":[
        "\u062c\u0632\u06cc\u0631\u06c1 \u0644\u0628"
    ],
    "name:zho_x_preferred":[
        "\u91cc\u5e03\u5cf6"
    ],
    "name:zho_x_variant":[
        "\u5229\u5e03\u5cf6"
    ],
    "qs:name":"Lib Island",
    "qs:photos_9r":0,
    "qs:photos_sr":0,
    "qs:pop_sr":"1",
    "wd:wordcount":163,
    "wof:name":"Lib Island",
    "wof:placetype":"locality",
    "wof:population":147
},
  "geometry": {"coordinates":[167.37860000000001,8.31444],"type":"Point"}
}