{
  "type": "Feature",
  "properties": {
    "gn:admin1_code":"320",
    "gn:asciiname":"Jelbon",
    "gn:cc2":"MH",
    "gn:country_code":"MH",
    "gn:dem":14,
    "gn:feature_class":"P",
    "gn:feature_code":"PPL",
    "gn:name":"Jelbon",
    "gn:population":0,
    "gn:timezone":"Pacific/Majuro",
    "iso:country":"MH",
    "wof:name":"Jelbon",
    "wof:placetype":"locality"
},
  "geometry": {"coordinates":[172.11438999999999,5.97122],"type":"Point"}
}