{
  "type": "Feature",
  "properties": {
    "gn:admin1_code":"410",
    "gn:asciiname":"Utrik",
    "gn:country_code":"MH",
    "gn:dem":10,
    "gn:feature_class":"P",
    "gn:feature_code":"PPLA",
    "gn:name":"Utrik",
    "gn:population":409,
    "gn:timezone":"Pacific/Majuro",
    "iso:country":"MH",
    "name:mah_x_preferred":[
        "Utr\u014dk"
    ],
    "name:und_x_variant":[
        "Utirik",
        "Utrik"
    ],
    "wof:name":"Utrik",
    "wof:placetype":"locality",
    "wof:population":409
},
  "geometry": {"coordinates":[169.84738999999999,11.22778],"type":"Point"}
}