{
  "type": "Feature",
  "properties": {
    "gn:admin1_code":"410",
    "gn:asciiname":"Utrik",
    "gn:country_code":"MH",
    "gn:dem":10,
    "gn:feature_class":"P",
    "gn:feature_code":"PPLA",
    "gn:name":"Utrik",
    "gn:population":409,
    "gn:timezone":"Pacific/Majuro",
    "iso:country":"MH",
    "name:ast_x_preferred":[
        "Atol\u00f3n d'Utirik"
    ],
    "name:bel_x_preferred":[
        "\u0423\u0442\u044b\u0440\u044b\u043a"
    ],
    "name:cat_x_preferred":[
        "Utirik"
    ],
    "name:ceb_x_preferred":[
        "Utrik"
    ],
    "name:deu_x_preferred":[
        "Utirik"
    ],
    "name:eus_x_preferred":[
        "Utirik"
    ],
    "name:fin_x_preferred":[
        "Utirik"
    ],
    "name:fra_x_preferred":[
        "Utirik"
    ],
    "name:glg_x_preferred":[
        "Atol Utirik"
    ],
    "name:ind_x_preferred":[
        "Atol Utirik"
    ],
    "name:ita_x_preferred":[
        "Utirik"
    ],
    "name:jpn_x_preferred":[
        "\u30a6\u30c1\u30ea\u30c3\u30af\u74b0\u7901"
    ],
    "name:kor_x_preferred":[
        "\uc6b0\ud2f0\ub9ac\ud06c \ud658\ucd08"
    ],
    "name:lit_x_preferred":[
        "Utirikas"
    ],
    "name:mah_x_preferred":[
        "Utr\u014dk"
    ],
    "name:mkd_x_preferred":[
        "\u0423\u0442\u0438\u0440\u0438\u043a"
    ],
    "name:pol_x_preferred":[
        "Utirik"
    ],
    "name:por_x_preferred":[
        "Atol Utirik"
    ],
    "name:rus_x_preferred":[
        "\u0423\u0442\u0438\u0440\u0438\u043a"
    ],
    "name:spa_x_preferred":[
        "Utirik"
    ],
    "name:swe_x_preferred":[
        "Utirik"
    ],
    "name:und_x_variant":[
        "Utirik",
        "Utrik"
    ],
    "name:zho_x_preferred":[
        "\u70cf\u8482\u91cc\u514b\u74b0\u7901"
    ],
    "wof:name":"Utrik",
    "wof:placetype":"locality",
    "wof:population":409
},
  "geometry": {"coordinates":[169.84738999999999,11.22778],"type":"Point"}
}