{
  "type": "Feature",
  "properties": {
    "gn:admin1_code":"170",
    "gn:asciiname":"Lib",
    "gn:country_code":"MH",
    "gn:dem":14,
    "gn:feature_class":"P",
    "gn:feature_code":"PPL",
    "gn:name":"Lib",
    "gn:population":0,
    "gn:timezone":"Pacific/Majuro",
    "iso:country":"MH",
    "name:swe_x_preferred":[
        "Lib"
    ],
    "wof:name":"Lib",
    "wof:placetype":"locality"
},
  "geometry": {"coordinates":[167.37499,8.31461],"type":"Point"}
}