{
  "type": "Feature",
  "properties": {
    "gn:admin1_code":"120",
    "gn:asciiname":"Populated Nanij Islands",
    "gn:country_code":"MH",
    "gn:dem":-9999,
    "gn:feature_class":"P",
    "gn:feature_code":"PPLS",
    "gn:name":"Populated Nanij Islands",
    "gn:population":0,
    "gn:timezone":"Pacific/Majuro",
    "iso:country":"MH",
    "wof:name":"Populated Nanij Islands",
    "wof:placetype":"locality"
},
  "geometry": {"coordinates":[169.50907000000001,6.23427],"type":"Point"}
}